Workbook

Sheet README
A1: SafeRise Protocol — financial model
A3: Prepared September 2026. Companion to the business summary.
A5: HOW TO READ THIS
A6: BLUE cells are inputs — change these. BLACK cells are formulas — do not overwrite.
A7: GREEN cells pull from another sheet. YELLOW cells are assumptions that most need your judgement.
A9: WHAT IS REAL AND WHAT IS MODELLED
A10: Sheet 'Invested to date' is measured — hours derived from counted output, not recalled.
A11: Every forward sheet is a model. No revenue exists. No conversion rate has been observed.
A12: Every forward number is an assumption you can change, not a projection from data.
A14: Cash actually spent to date is NOT in this model — only replacement cost. Enter your
A15: real cash outlay in 'Invested to date' cell B14 if you want the model to carry it.
A17: SHEETS
... A28: They are marked yellow. A backer should test those cells first — they drive everything.

Sheet Invested to date
A1: Invested to date — replacement cost
A2: Measured from counted output, not recalled. Source: Business Development Assessment, September 2026 (supersedes the 8 Sep baseline of 1,770 h / $155,577).
A4: Workstream | B4: Hours | C4: Rate ($/h) | D4: Replacement cost
A5: Product & content | B5: 940 | C5: 89.1 | D5: =B5*C5 -> 83754
A6: Web & engineering | B6: 972 | C6: 76 | D6: =B6*C6 -> 73872
A7: Business & commercial | B7: 404 | C7: 111.9 | D7: =B7*C7 -> 45207.6
A8: Total | B8: =SUM(B5:B7) -> 2316 | D8: =SUM(D5:D7) -> 202833.6
A10: Elapsed equivalent (weeks at 40 h) | B10: =B8/40 -> 57.9
A11: Elapsed equivalent (months) | B11: =B8/40/4.33 -> 13.371824
A13: Actual cash spent to date (€) — YOU FILL THIS. Entity: Kenor International B.V.
A14: Domains, hosting, ElevenLabs, tooling, any contractor payments. Replacement cost above is not cash out.
A16: This is replacement cost, not a valuation. Investors price traction, not sweat equity. Present it as an honest floor: below this, an acquirer gets the asset for less than it cost to make.

Sheet Assumptions
A1: Assumptions — every lever
A2: Yellow = untested, drives everything, test these first.
A4: PRICING — settled
A5: Membership, monthly (€) | B5: 19 | C5: Track 01 free; €19 opens every other track. Supersedes the €19/29/39 ladder (SR-381)
A6: Membership, annual (€) | B6: 190 | C6: Ten months for twelve
A7: Workshop, per person (€) | B7: 39 | C7: 90 min, remote. NOTE: pitch deck slide 13 says €29 — reconcile
A8: One-to-one, per session (€) | B8: 129 | C8: Three for €349
A9: Organisational pilot (€) | B9: 4500 | C9: Credited against Foundation within 60 days
A10: Organisation workshop (€) | B10: 1800 | C10: First paid corporate engagement
A11: Half-day retreat (€) | B11: 3500 | C11: Core offer, banded by size (€1,800 small)
A12: Annual access, band 1 (€) | B12: 9000 | C12: BANDED BY HEADCOUNT, never per seat — per-seat implies counting usage
A13: Annual access, band 2 (€) | B13: 38000 | C13: Mid-size organisation
A14: Annual access, band 3 (€) | B14: 95000 | C14: Large. Requires a second facilitator before it can be sold
A16: B2C — UNTESTED
A17: Free sign-ups, month 1 | B17: 250 | C17: After noindex removal. No data — a guess
A18: Monthly growth in sign-ups | B18: 0.35 | C18: Compounding. Organic + content
A19: Free → paid conversion | B19: 0.04 | C19: 4% is a cautious freemium figure. Untested
A20: Monthly churn, paid | B20: 0.06 | C20: 6% monthly. Consumer wellness is churn-heavy
A21: Share choosing annual | B21: 0.25 | C21: Annual improves cash but lowers monthly recognised
A22: Monthly growth, months 13-24 | B22: 0.08 | C22: Growth MUST taper. Compounding 35% for two years is fantasy, not a forecast
A24: B2B — UNTESTED
A25: Pilots closed per quarter (steady) | B25: 2 | C25: From month 7. Founder-led selling
A26: Pilot → Foundation conversion | B26: 0.4 | C26: Credit makes the full contract half-decided
A27: First B2B revenue month | B27: 4 | C27: Pilot can be sold before the platform is ready
A28: Share of contracts at Practice | B28: 0.2 | C28: Most land at Foundation first
A30: COSTS — monthly
A31: Hosting, domains, CDN (€) | B31: 120 | C31: Current run rate
A32: Tooling — ElevenLabs, design, dev (€) | B32: 350 | C32: Audio production is the bulk
A33: Transactional + marketing email (€) | B33: 60 | C33: Not yet chosen
A34: Payment processing (% of revenue) | B34: 0.05 | C34: Paddle merchant-of-record, incl. VAT handling
A35: Legal & accounting, monthly average (€) | B35: 400 | C35: Entity, terms, DPA, clinical contracting
A36: Marketing & content (€/month) | B36: 800 | C36: Deliberately low — organic first
A37: AI tooling — Claude Max 20x, ChatGPT, Runway, API (€/month) | B37: 250 | C37: Substitutes for contract dev, design and video. Scales to ~2,300/mo at full team
A39: PEOPLE — monthly cost when engaged
A40: Clinician retainer (€/month) | B40: 400 | C40: Up to 4 h; €120/h beyond. Gates all live delivery
A41: Facilitator, part-time (€/month) | B41: 2200 | C41: Needed before Practice tier is sold
A42: Contract developer (€/month) | B42: 4500 | C42: Org data model, SSO, admin console
A43: Founder salary (€/month) | B43: 0 | C43: Zero until revenue supports it. Change to model a raise

Sheet B2C 3-month
A1: B2C — first three months
A2: Assumes noindex removed at month 1. Every figure derives from Assumptions.
B4: Month 1 | C4: Month 2 | D4: Month 3 | E4: Quarter
A5: Free sign-ups added | B5: =Assumptions!$B$17 -> 250 | C5: =B5*(1+Assumptions!$B$18) -> 337.5 | D5: =C5*(1+Assumptions!$B$18) -> 455.625 | E5: =SUM(B5:D5) -> 1043.125
A6: Cumulative free accounts | B6: =B5 -> 250 | C6: =B6+C5 -> 587.5 | D6: =C6+D5 -> 1043.125 | E6: =D6 -> 1043.125
A7: New paying members | B7: =B5*Assumptions!$B$19 -> 10 | C7: =C5*Assumptions!$B$19 -> 13.5 | D7: =D5*Assumptions!$B$19 -> 18.225 | E7: =SUM(B7:D7) -> 41.725
A8: Paying members (end of month) | B8: =B7 -> 10 | C8: =B8*(1-Assumptions!$B$20)+C7 -> 22.9 | D8: =C8*(1-Assumptions!$B$20)+D7 -> 39.751 | E8: =D8 -> 39.751
A10: Subscription revenue (€) | B10: =B8*Assumptions!$B$5 -> 190 | C10: =C8*Assumptions!$B$5 -> 435.1 | D10: =D8*Assumptions!$B$5 -> 755.269 | E10: =SUM(B10:D10) -> 1380.369
A11: Workshop revenue (€) | B11: =0 -> 0 | C11: =0 -> 0 | D11: =0 -> 0 | E11: =SUM(B11:D11) -> 0
A12: Total revenue (€) | B12: =B10+B11 -> 190 | C12: =C10+C11 -> 435.1 | D12: =D10+D11 -> 755.269 | E12: =SUM(B12:D12) -> 1380.369
A14: Operating cost (€) | B14: =(Assumptions!$B$31+Assumptions!$B$32+Assumptions!$B$33+Assumptions!$B$35+Assumptions!$B$36+Assumptions!$B$43)+B12*Assumptions!$B$34 -> 1739.5 | C14: =(Assumptions!$B$31+Assumptions!$B$32+Assumptions!$B$33+Assumptions!$B$35+Assumptions!$B$36+Assumptions!$B$43)+C12*Assumptions!$B$34 -> 1751.755 | D14: =(Assumptions!$B$31+Assumptions!$B$32+Assumptions!$B$33+Assumptions!$B$35+Assumptions!$B$36+Assumptions!$B$43)+D12*Assumptions!$B$34 -> 1767.7634 | E14: =SUM(B14:D14) -> 5259.0184
A15: Net (€) | B15: =B12-B14 -> -1549.5 | C15: =C12-C14 -> -1316.655 | D15: =D12-D14 -> -1012.4945 | E15: =E12-E14 -> -3878.6494
A18: Capital required for the quarter (€) | B18: =-MIN(0,E15) -> 3878.6494
A20: Workshops are zero because escalation criteria are not agreed — nothing live can be sold until they are.
A21: Three months does not reach profitability at any plausible conversion rate. The purpose of this quarter is a conversion number, not revenue.

Sheet B2B 6-month
A1: B2B — six months to a sellable business
A2: Month 1 here = month 1 of the raise. B2B revenue cannot begin before the clinical gate closes.
B4: M1 | C4: M2 | D4: M3 | E4: M4 | F4: M5 | G4: M6 | H4: Total
A5: Pilots closed | B5: 0 | C5: 0 | D5: 1 | E5: 1 | F5: 2 | G5: 2 | H5: =SUM(B5:G5) -> 6
A6: Foundation contracts signed | B6: 0 | C6: 0 | D6: 0 | E6: 0 | F6: 1 | G6: 1 | H6: =SUM(B6:G6) -> 2
A8: Pilot revenue (€) | B8: =B5*Assumptions!$B$9 -> 0 | C8: =C5*Assumptions!$B$9 -> 0 | D8: =D5*Assumptions!$B$9 -> 4500 | E8: =E5*Assumptions!$B$9 -> 4500 | F8: =F5*Assumptions!$B$9 -> 9000 | G8: =G5*Assumptions!$B$9 -> 9000 | H8: =SUM(B8:G8) -> 27000
A9: Foundation revenue, billed annually (€) | B9: =B6*Assumptions!$B$12 -> 0 | C9: =C6*Assumptions!$B$12 -> 0 | D9: =D6*Assumptions!$B$12 -> 0 | E9: =E6*Assumptions!$B$12 -> 0 | F9: =F6*Assumptions!$B$12 -> 9000 | G9: =G6*Assumptions!$B$12 -> 9000 | H9: =SUM(B9:G9) -> 18000
A10: Total B2B revenue (€) | B10: =B8+B9 -> 0 | C10: =C8+C9 -> 0 | D10: =D8+D9 -> 4500 | E10: =E8+E9 -> 4500 | F10: =F8+F9 -> 18000 | G10: =G8+G9 -> 18000 | H10: =SUM(B10:G10) -> 45000
A12: Build cost — what the six months buys
A13: Contract developer (€) | B13: =Assumptions!$B$42 -> 4500 | C13: =Assumptions!$B$42 -> 4500 | D13: =Assumptions!$B$42 -> 4500 | E13: =Assumptions!$B$42 -> 4500 | F13: =Assumptions!$B$42 -> 4500 | G13: =Assumptions!$B$42 -> 4500 | H13: =SUM(B13:G13) -> 27000
A14: Clinician retainer (€) | B14: =Assumptions!$B$40 -> 400 | C14: =Assumptions!$B$40 -> 400 | D14: =Assumptions!$B$40 -> 400 | E14: =Assumptions!$B$40 -> 400 | F14: =Assumptions!$B$40 -> 400 | G14: =Assumptions!$B$40 -> 400 | H14: =SUM(B14:G14) -> 2400
A15: Facilitator (€) | B15: 0 | C15: 0 | D15: 0 | E15: =Assumptions!$B$41 -> 2200 | F15: =Assumptions!$B$41 -> 2200 | G15: =Assumptions!$B$41 -> 2200 | H15: =SUM(B15:G15) -> 6600
A16: Shared operating cost (€) | B16: =(Assumptions!$B$31+Assumptions!$B$32+Assumptions!$B$33+Assumptions!$B$35+Assumptions!$B$36+Assumptions!$B$37+Assumptions!$B$43) -> 1980 | C16: =(Assumptions!$B$31+Assumptions!$B$32+Assumptions!$B$33+Assumptions!$B$35+Assumptions!$B$36+Assumptions!$B$37+Assumptions!$B$43) -> 1980 | D16: =(Assumptions!$B$31+Assumptions!$B$32+Assumptions!$B$33+Assumptions!$B$35+Assumptions!$B$36+Assumptions!$B$37+Assumptions!$B$43) -> 1980 | E16: =(Assumptions!$B$31+Assumptions!$B$32+Assumptions!$B$33+Assumptions!$B$35+Assumptions!$B$36+Assumptions!$B$37+Assumptions!$B$43) -> 1980 | F16: =(Assumptions!$B$31+Assumptions!$B$32+Assumptions!$B$33+Assumptions!$B$35+Assumptions!$B$36+Assumptions!$B$37+Assumptions!$B$43) -> 1980 | G16: =(Assumptions!$B$31+Assumptions!$B$32+Assumptions!$B$33+Assumptions!$B$35+Assumptions!$B$36+Assumptions!$B$37+Assumptions!$B$43) -> 1980 | H16: =SUM(B16:G16) -> 11880
A17: Total cost (€) | B17: =B13+B14+B15+B16 -> 6880 | C17: =C13+C14+C15+C16 -> 6880 | D17: =D13+D14+D15+D16 -> 6880 | E17: =E13+E14+E15+E16 -> 9080 | F17: =F13+F14+F15+F16 -> 9080 | G17: =G13+G14+G15+G16 -> 9080 | H17: =SUM(B17:G17) -> 47880
A18: Net (€) | B18: =B10-B17 -> -6880 | C18: =C10-C17 -> -6880 | D18: =D10-D17 -> -2380 | E18: =E10-E17 -> -4580 | F18: =F10-F17 -> 8920 | G18: =G10-G17 -> 8920 | H18: =SUM(B18:G18) -> -2880
A19: Cumulative cash (€) | B19: =B18 -> -6880 | C19: =B19+C18 -> -13760 | D19: =C19+D18 -> -16140 | E19: =D19+E18 -> -20720 | F19: =E19+F18 -> -11800 | G19: =F19+G18 -> -2880
A22: Peak cash requirement (€) | B22: =-MIN(B19:G19) -> 20720
A23: Net over the six months (€) | B23: =G19 -> -2880
A25: Pilots begin month 3 — after escalation criteria are agreed, not before.
A26: Facilitator joins month 4, before the first Foundation contract is delivered, not after it is signed.
A27: Foundation is billed annually, so month-5 and month-6 revenue is cash in, not recognised revenue.

Sheet Forecast 24-month
A1: 24-month forecast — both lines
A2: Illustrative. Every driver lives in Assumptions. Change one cell and the whole sheet moves.
B4: M1 | C4: M2 | D4: M3 | E4: M4 | F4: M5 | G4: M6 | H4: M7 | I4: M8 | J4: M9 | K4: M10 | L4: M11 | M4: M12 | N4: M13 | O4: M14 | P4: M15 | Q4: M16 | R4: M17 | S4: M18 | T4: M19 | U4: M20 | V4: M21 | W4: M22 | X4: M23 | Y4: M24
A5: Free sign-ups added | B5: =Assumptions!$B$17 -> 250 | C5: =B5*(1+Assumptions!$B$18) -> 337.5 | D5: =C5*(1+Assumptions!$B$18) -> 455.625 | E5: =D5*(1+Assumptions!$B$18) -> 615.09375 | F5: =E5*(1+Assumptions!$B$18) -> 830.37656 | G5: =F5*(1+Assumptions!$B$18) -> 1121.0084 | H5: =G5*(1+Assumptions!$B$18) -> 1513.3613 | I5: =H5*(1+Assumptions!$B$18) -> 2043.0377 | J5: =I5*(1+Assumptions!$B$18) -> 2758.1009 | ... M5: =L5*(1+Assumptions!$B$18) -> 6785.9626 | N5: =M5*(1+Assumptions!$B$22) -> 7328.8396 | O5: =N5*(1+Assumptions!$B$22) -> 7915.1468 | P5: =O5*(1+Assumptions!$B$22) -> 8548.3585 | Q5: =P5*(1+Assumptions!$B$22) -> 9232.2272 | R5: =Q5*(1+Assumptions!$B$22) -> 9970.8054 | S5: =R5*(1+Assumptions!$B$22) -> 10768.47 | T5: =S5*(1+Assumptions!$B$22) -> 11629.947 | U5: =T5*(1+Assumptions!$B$22) -> 12560.343 | ... Y5: =X5*(1+Assumptions!$B$22) -> 17088.208
A6: New paying | B6: =B5*Assumptions!$B$19 -> 10 | C6: =C5*Assumptions!$B$19 -> 13.5 | D6: =D5*Assumptions!$B$19 -> 18.225 | E6: =E5*Assumptions!$B$19 -> 24.60375 | F6: =F5*Assumptions!$B$19 -> 33.215063 | G6: =G5*Assumptions!$B$19 -> 44.840334 | H6: =H5*Assumptions!$B$19 -> 60.534451 | I6: =I5*Assumptions!$B$19 -> 81.721509 | ... Y6: =Y5*Assumptions!$B$19 -> 683.52833
A7: Paying members | B7: =B6 -> 10 | C7: =B7*(1-Assumptions!$B$20)+C6 -> 22.9 | D7: =C7*(1-Assumptions!$B$20)+D6 -> 39.751 | E7: =D7*(1-Assumptions!$B$20)+E6 -> 61.96969 | F7: =E7*(1-Assumptions!$B$20)+F6 -> 91.466571 | G7: =F7*(1-Assumptions!$B$20)+G6 -> 130.81891 | H7: =G7*(1-Assumptions!$B$20)+H6 -> 183.50423 | I7: =H7*(1-Assumptions!$B$20)+I6 -> 254.21548 | J7: =I7*(1-Assumptions!$B$20)+J6 -> 349.28659 | ... Y7: =X7*(1-Assumptions!$B$20)+Y6 -> 4696.2121
A8: B2C revenue (€) | B8: =B7*Assumptions!$B$5 -> 190 | C8: =C7*Assumptions!$B$5 -> 435.1 | D8: =D7*Assumptions!$B$5 -> 755.269 | E8: =E7*Assumptions!$B$5 -> 1177.4241 | F8: =F7*Assumptions!$B$5 -> 1737.8649 | G8: =G7*Assumptions!$B$5 -> 2485.5593 | H8: =H7*Assumptions!$B$5 -> 3486.5803 | I8: =I7*Assumptions!$B$5 -> 4830.0942 | ... Y8: =Y7*Assumptions!$B$5 -> 89228.03
A10: Pilots closed | B10: 0 | C10: 0 | D10: 1 | E10: 1 | F10: =Assumptions!$B$25/3 -> 0.66666667 | G10: =Assumptions!$B$25/3 -> 0.66666667 | H10: =Assumptions!$B$25/3 -> 0.66666667 | I10: =Assumptions!$B$25/3 -> 0.66666667 | J10: =Assumptions!$B$25/3 -> 0.66666667 | K10: =Assumptions!$B$25/3 -> 0.66666667 | L10: =Assumptions!$B$25/3 -> 0.66666667 | M10: =Assumptions!$B$25/3 -> 0.66666667 | ... Y10: =Assumptions!$B$25/3 -> 0.66666667
A11: Foundation contracts (cumulative) | B11: 0 | C11: 0 | D11: 0 | E11: 0 | F11: =E11+D10*Assumptions!$B$26 -> 0.4 | G11: =F11+E10*Assumptions!$B$26 -> 0.8 | H11: =G11+F10*Assumptions!$B$26 -> 1.0666667 | I11: =H11+G10*Assumptions!$B$26 -> 1.3333333 | J11: =I11+H10*Assumptions!$B$26 -> 1.6 | K11: =J11+I10*Assumptions!$B$26 -> 1.8666667 | L11: =K11+J10*Assumptions!$B$26 -> 2.1333333 | M11: =L11+K10*Assumptions!$B$26 -> 2.4 | ... Y11: =X11+W10*Assumptions!$B$26 -> 5.6
A12: B2B revenue (€) | B12: =B10*Assumptions!$B$9+B11*Assumptions!$B$12/12 -> 0 | C12: =C10*Assumptions!$B$9+C11*Assumptions!$B$12/12 -> 0 | D12: =D10*Assumptions!$B$9+D11*Assumptions!$B$12/12 -> 4500 | E12: =E10*Assumptions!$B$9+E11*Assumptions!$B$12/12 -> 4500 | F12: =F10*Assumptions!$B$9+F11*Assumptions!$B$12/12 -> 3300 | G12: =G10*Assumptions!$B$9+G11*Assumptions!$B$12/12 -> 3600 | H12: =H10*Assumptions!$B$9+H11*Assumptions!$B$12/12 -> 3800 | I12: =I10*Assumptions!$B$9+I11*Assumptions!$B$12/12 -> 4000 | ... Y12: =Y10*Assumptions!$B$9+Y11*Assumptions!$B$12/12 -> 7200
A14: Total revenue (€) | B14: =B8+B12 -> 190 | C14: =C8+C12 -> 435.1 | D14: =D8+D12 -> 5255.269 | E14: =E8+E12 -> 5677.4241 | F14: =F8+F12 -> 5037.8649 | G14: =G8+G12 -> 6085.5593 | H14: =H8+H12 -> 7286.5803 | I14: =I8+I12 -> 8830.0942 | ... Y14: =Y8+Y12 -> 96428.03
A15: Total cost (€) | B15: =(Assumptions!$B$31+Assumptions!$B$32+Assumptions!$B$33+Assumptions!$B$35+Assumptions!$B$36+Assumptions!$B$43)+Assumptions!$B$42+0+0+B14*Assumptions!$B$34 -> 6239.5 | C15: =(Assumptions!$B$31+Assumptions!$B$32+Assumptions!$B$33+Assumptions!$B$35+Assumptions!$B$36+Assumptions!$B$43)+Assumptions!$B$42+0+Assumptions!$B$40+C14*Assumptions!$B$34 -> 6651.755 | D15: =(Assumptions!$B$31+Assumptions!$B$32+Assumptions!$B$33+Assumptions!$B$35+Assumptions!$B$36+Assumptions!$B$43)+Assumptions!$B$42+0+Assumptions!$B$40+D14*Assumptions!$B$34 -> 6892.7635 | E15: =(Assumptions!$B$31+Assumptions!$B$32+Assumptions!$B$33+Assumptions!$B$35+Assumptions!$B$36+Assumptions!$B$43)+Assumptions!$B$42+Assumptions!$B$41+Assumptions!$B$40+E14*Assumptions!$B$34 -> 9113.8712 | F15: =(Assumptions!$B$31+Assumptions!$B$32+Assumptions!$B$33+Assumptions!$B$35+Assumptions!$B$36+Assumptions!$B$43)+Assumptions!$B$42+Assumptions!$B$41+Assumptions!$B$40+F14*Assumptions!$B$34 -> 9081.8932 | G15: =(Assumptions!$B$31+Assumptions!$B$32+Assumptions!$B$33+Assumptions!$B$35+Assumptions!$B$36+Assumptions!$B$43)+Assumptions!$B$42+Assumptions!$B$41+Assumptions!$B$40+G14*Assumptions!$B$34 -> 9134.278 | H15: =(Assumptions!$B$31+Assumptions!$B$32+Assumptions!$B$33+Assumptions!$B$35+Assumptions!$B$36+Assumptions!$B$43)+0+Assumptions!$B$41+Assumptions!$B$40+H14*Assumptions!$B$34 -> 4694.329 | I15: =(Assumptions!$B$31+Assumptions!$B$32+Assumptions!$B$33+Assumptions!$B$35+Assumptions!$B$36+Assumptions!$B$43)+0+Assumptions!$B$41+Assumptions!$B$40+I14*Assumptions!$B$34 -> 4771.5047 | J15: =(Assumptions!$B$31+Assumptions!$B$32+Assumptions!$B$33+Assumptions!$B$35+Assumptions!$B$36+Assumptions!$B$43)+0+Assumptions!$B$41+Assumptions!$B$40+J14*Assumptions!$B$34 -> 4871.8223 | K15: =(Assumptions!$B$31+Assumptions!$B$32+Assumptions!$B$33+Assumptions!$B$35+Assumptions!$B$36+Assumptions!$B$43)+0+Assumptions!$B$41+Assumptions!$B$40+K14*Assumptions!$B$34 -> 5003.4035 | L15: =(Assumptions!$B$31+Assumptions!$B$32+Assumptions!$B$33+Assumptions!$B$35+Assumptions!$B$36+Assumptions!$B$43)+0+Assumptions!$B$41+Assumptions!$B$40+L14*Assumptions!$B$34 -> 5177.2116 | M15: =(Assumptions!$B$31+Assumptions!$B$32+Assumptions!$B$33+Assumptions!$B$35+Assumptions!$B$36+Assumptions!$B$43)+0+Assumptions!$B$41+Assumptions!$B$40+M14*Assumptions!$B$34 -> 5408.0455 | N15: =(Assumptions!$B$31+Assumptions!$B$32+Assumptions!$B$33+Assumptions!$B$35+Assumptions!$B$36+Assumptions!$B$43)+0+Assumptions!$B$41+Assumptions!$B$40+N14*Assumptions!$B$34 -> 5646.2586 | O15: =(Assumptions!$B$31+Assumptions!$B$32+Assumptions!$B$33+Assumptions!$B$35+Assumptions!$B$36+Assumptions!$B$43)+0+Assumptions!$B$41+Assumptions!$B$40+O14*Assumptions!$B$34 -> 5893.0587 | ... Y15: =(Assumptions!$B$31+Assumptions!$B$32+Assumptions!$B$33+Assumptions!$B$35+Assumptions!$B$36+Assumptions!$B$43)+0+Assumptions!$B$41+Assumptions!$B$40+Y14*Assumptions!$B$34 -> 9151.4015
A16: Net (€) | B16: =B14-B15 -> -6049.5 | C16: =C14-C15 -> -6216.655 | D16: =D14-D15 -> -1637.4944 | E16: =E14-E15 -> -3436.4471 | F16: =F14-F15 -> -4044.0284 | G16: =G14-G15 -> -3048.7187 | H16: =H14-H15 -> 2592.2513 | I16: =I14-I15 -> 4058.5895 | ... Y16: =Y14-Y15 -> 87276.628
A17: Cumulative net (€) | B17: =B16 -> -6049.5 | C17: =B17+C16 -> -12266.155 | D17: =C17+D16 -> -13903.649 | E17: =D17+E16 -> -17340.097 | F17: =E17+F16 -> -21384.125 | G17: =F17+G16 -> -24432.844 | H17: =G17+H16 -> -21840.592 | I17: =H17+I16 -> -17782.003 | J17: =I17+J16 -> -11817.38 | ... Y17: =X17+Y16 -> 637194.67
A20: Peak funding need (€) | B20: =-MIN(B17:Y17) -> 24432.844
A21: Month of peak need | B21: =MATCH(MIN(B17:Y17),B17:Y17,0) -> 6
A23: Peak funding need is the number a backer actually cares about — not total cost, but how deep the hole gets before it turns.

Sheet Team & cost
A1: Team structure — who is needed, and when
A2: Ordered by what unblocks the most. Nothing here is currently contracted.
A4: Role | B4: What it unblocks | C4: Needed from | D4: Monthly (€) | E4: Basis
A5: Founder | B5: Method, content, enterprise sales, product direction | C5: Now | D5: =Assumptions!$B$43 -> 0 | E5: Unpaid until revenue supports it
A6: Clinician (retainer) | B6: Escalation criteria; gates ALL live delivery and both live tiers | C6: Month 1 | D6: =Assumptions!$B$40 -> 400 | E6: €400/mo up to 4h, €120/h beyond
A7: Contract developer | B7: Org account model, seat provisioning, admin, SSO, invoicing | C7: Month 1 | D7: =Assumptions!$B$42 -> 4500 | E7: 6-month engagement
A8: Facilitator #1 | B8: Delivers pilots and Foundation sessions | C8: Month 4 | D8: =Assumptions!$B$41 -> 2200 | E8: Part-time
A9: Facilitator #2 | B9: Required before Partner tier can be sold at all | C9: Month 13 | D9: =Assumptions!$B$41 -> 2200 | E9: Part-time, scales with pipeline
A10: Content producer | B10: Sleep & Recovery, then the substrate tracks | C10: Month 3 | D10: 2800 | E10: Part-time or contract
A11: Fractional CFO / bookkeeper | B11: Entity, invoicing, VAT, board reporting | C11: Month 2 | D11: 450 | E11: Monthly
A12: Total at full complement | D12: =SUM(D5:D11) -> 9300
A14: The clinician is the single highest-leverage hire: without agreed escalation criteria, no workshop, no 1:1 and no organisational tier can be sold.
A15: Facilitator capacity — not demand — is the ceiling on B2B. Foundation costs ~6 facilitator hours a year per account; Practice ~22; Partner ~60.
A16: Do not sell Partner before Facilitator #2 exists. One in-person day with a scheduling conflict is a broken contract.

Sheet Capital ask
A1: Capital ask — what the money is for
A2: Capital is not needed to build the product. It exists. It is needed to buy delivery capacity and evidence.
A4: Use | B4: Why | C4: Months | D4: Amount (€)
A5: Clinical governance | B5: Retainer + contracting. Unblocks every live tier | C5: 12 | D5: =Assumptions!$B$40*12 -> 4800
A6: Engineering | B6: Org account model, seats, admin, SSO, invoicing | C6: 6 | D6: =Assumptions!$B$42*6 -> 27000
A7: Facilitation capacity | B7: Facilitator #1 from month 4 | C7: 9 | D7: =Assumptions!$B$41*9 -> 19800
A8: Content — substrate layer | B8: Sleep & Recovery, Nutrition, Strength & Return | C8: 10 | D8: =2800*10 -> 28000
A9: Operating run rate | B9: Hosting, tooling, email, legal, accounting | C9: 12 | D9: =(Assumptions!$B$31+Assumptions!$B$32+Assumptions!$B$33+Assumptions!$B$35)*12 -> 11160
A10: AI tooling | B10: Claude Max and Code, ChatGPT, Runway, API — replaces contract build | C10: 12 | D10: =Assumptions!$B$37*12 -> 3000
A11: Marketing & content | B11: Deliberately low — organic first | C11: 12 | D11: =Assumptions!$B$36*12 -> 9600
A12: Pilots run at or near cost | B12: Two, to produce the first evidence | C12: — | D12: 4000
A13: Contingency | B13: 15% — the gaps you cannot see yet | C13: — | D13: =SUM(D5:D12)*0.15 -> 16104
A14: Total capital ask | D14: =SUM(D5:D13) -> 123464
A16: Cross-check: see 'Forecast 24-month' — peak funding need
A18: Founder salary is set to zero in Assumptions. A backer will ask — decide whether to model a raise before the conversation.
A19: This ask buys twelve months against three gaps: clinical governance, delivery capacity, evidence. It does not buy product development.
A20: The milestone that matters is not revenue. It is two written pilot findings reports and a named reference customer.
